README
setup.cfg
setup.py
src/tangentdeployer/__init__.py
src/tangentdeployer.egg-info/PKG-INFO
src/tangentdeployer.egg-info/SOURCES.txt
src/tangentdeployer.egg-info/dependency_links.txt
src/tangentdeployer.egg-info/requires.txt
src/tangentdeployer.egg-info/top_level.txt
src/tangentdeployer/aws/__init__.py
src/tangentdeployer/aws/autoscale.py
src/tangentdeployer/aws/ec2.py
src/tangentdeployer/aws/elb.py
src/tangentdeployer/aws/route53.py
src/tangentdeployer/aws/s3.py
src/tangentdeployer/aws/utils.py
src/tangentdeployer/internal/__init__.py
src/tangentdeployer/internal/utils.py