Metadata-Version: 1.1
Name: tangentdeployer
Version: 0.1.21
Summary: A Fabric deploy script for AWS based projects
Home-page: https://github.com/tangentlabs/tangent-deployer
Author: Chris McKinnel
Author-email: chris.mckinnel@tangentsnowball.com
License: UNKNOWN
Download-URL: https://github.com/tangentlabs/tangent-deployer/tarball/0.1.21
Keywords: deployment,fabric,tangent
Platform: UNKNOWN
